fassert/__init__.py
fassert-0.3.dist-info/LICENSE.txt
fassert-0.3.dist-info/METADATA
fassert-0.3.dist-info/WHEEL
fassert-0.3.dist-info/top_level.txt
fassert-0.3.dist-info/RECORD
