Metadata-Version: 2.1
Name: fassert
Version: 0.3
Summary: UNKNOWN
Home-page: https://github.com/SourceCode-AI/fassert
Author: Martin Carnogursky
Author-email: admin@sourcecode.ai
License: UNKNOWN
Keywords: fuzzy,assert,matching,nested
Platform: UNKNOWN
Classifier: Intended Audience :: Developers
Classifier: Programming Language :: Python :: 3 :: Only
Classifier: License :: OSI Approved :: MIT License
Classifier: Operating System :: OS Independent
Requires-Python: >=3.8
License-File: LICENSE.txt
